clname.py
clname-1.0.0.dist-info/LICENSE
clname-1.0.0.dist-info/METADATA
clname-1.0.0.dist-info/WHEEL
clname-1.0.0.dist-info/entry_points.txt
clname-1.0.0.dist-info/top_level.txt
clname-1.0.0.dist-info/RECORD
