Metadata-Version: 2.1
Name: clname
Version: 1.0.0
Summary: Cleans filenames to make them shell-friendly
Home-page: https://github.com/lepperdinger/clname
Author: Stefan Lepperdinger
Author-email: lepperdinger.stefan@gmail.com
License: UNKNOWN
Platform: UNKNOWN
Classifier: Programming Language :: Python :: 3
Classifier: License :: OSI Approved :: GNU General Public License v3 (GPLv3)
Classifier: Operating System :: POSIX :: Linux
Requires-Python: >=3.6
License-File: LICENSE
